{
"Configuration":"Corse GT (M)",
"Performance Class":"10",
"Weight":1305,
"default_color_3":"Alabastro",
"default_color_2":"Blu Marina",
"Config Type":"Factory",
"Transmission":"Manual",
"PowerPeakRPM":"6750 - 7850",
"default_color":"Rosso Scarlatto",
"Torque":518.051,
"Power":469.256,
"Value":600000,
"Weight/Power":2.78252,
"TorquePeakRPM":"4200 - 5450",
"Drivetrain":"RWD",
"Description":"Exclusive 'Corse' Version with a twin-turbocharged V8 and completely redesigned exterior, The GT version features some Competizione-inspired visual changes and tweaked turbos"
}