{
"0-120 mph":13.6,
"Performance Class":"8",
"Drivetrain":"AWD",
"0-300 km/h":57.1,
"100-200 km/h":11.7,
"Body Style":"Coupe",
"Braking G":1.151,
"0-200 km/h":16.1,
"Value":118000,
"0-100 km/h":4.5,
"TorquePeakRPM":"1550 - 4950",
"0-100 mph":10.2,
"Description":"Limited edition Kc6tx with a two-tone paintjob and exclusive spoiler",
"Configuration":"Kc6tx Hummel (M)",
"Top Speed":87.6388,
"default_color":"Solar Yellow",
"default_color_2":"Carbonite",
"60-100 mph":6,
"0-60 mph":4.3,
"Config Type":"Factory",
"100-0 km/h":34.1,
"PowerPeakRPM":"5100 - 6350",
"Transmission":"Manual",
"Torque":472.507,
"Power":330.694,
"Off-Road Score":27,
"Weight/Power":4.77273,
"60-0 mph":103.8,
"60-120 mph":9.7,
"Weight":1575
}