{
"0-120 mph":42,
"Performance Class":"4",
"Drivetrain":"RWD",
"100-200 km/h":34.9,
"0-100 mph":21.8,
"Value":4100,
"0-100 km/h":8.4,
"TorquePeakRPM":"2700 - 4600",
"Weight":1820,
"Description":"Limited edition Bruckell model based on the GL, but features chrome trim and Luxe hubcaps.",
"Configuration":"Road Cruiser GL Classic Edition (A)",
"PowerPeakRPM":5200,
"default_color":"Seafoam Green",
"60-100 mph":14,
"0-60 mph":7.8,
"Config Type":"Factory",
"100-0 km/h":37.4,
"Top Speed":57.9939,
"Transmission":"Automatic",
"Torque":315.066,
"Off-Road Score":25,
"Power":216.693,
"Weight/Power":8.42593,
"60-0 mph":114.4,
"60-120 mph":34.1,
"0-200 km/h":43.3
}