{
"Performance Class":"1",
"Drivetrain":"RWD",
"Body Style":"Semi Truck",
"Value":70000,
"0-100 km/h":21.8,
"TorquePeakRPM":"850 - 1550",
"0-100 mph":63.8,
"Description":"A truck designed for speed races, with 900hp and a top speed of more than 200km/h",
"Configuration":"T65 Race (M)",
"Braking G":0.847,
"default_color":"Sea Blue",
"60-100 mph":43,
"0-60 mph":20.8,
"Config Type":"Factory",
"100-0 km/h":46.4,
"Top Speed":48.2458,
"Power":315.692,
"Torque":1479.63,
"Weight":6600,
"Off-Road Score":28,
"Weight/Power":20.9524,
"60-0 mph":139.7,
"Transmission":"Manual",
"PowerPeakRPM":"1550 - 2100"
}